attentionme/__init__.py
attentionme/adjust_brightness.py
attentionme/crop.py
attentionme/enlargement.py
attentionme/pointing.py
attentionme/remove_background.py
attentionme/segmentation.py
attentionme/zoom_in.py
attentionme-0.1.1.dist-info/LICENSE
attentionme-0.1.1.dist-info/METADATA
attentionme-0.1.1.dist-info/WHEEL
attentionme-0.1.1.dist-info/top_level.txt
attentionme-0.1.1.dist-info/RECORD
