Metadata-Version: 2.1
Name: attentionme
Version: 0.1.1
Summary: A library for person-focused image processing
Home-page: https://github.com/Looking-4-Attention/AttentionMe
Author: Aenoc Woo, Dami Lee, Namhoon Cho, Hyunsoo Kim
Author-email: Aenoc Woo <wwwwje2008@gmail.com>, Dami Lee <daming@hanyang.ac.kr>, Namhoon Cho <lovin6109@gmail.com>, Hyunsoo Kim <hyun12278@hangang.ac.kr>
License: MIT
Project-URL: Homepage, https://github.com/Looking-4-Attention/AttentionMe
Project-URL: Issues, https://github.com/Looking-4-Attention/AttentionMe/issues
Classifier: Programming Language :: Python :: 3
Classifier: License :: OSI Approved :: MIT License
Classifier: Operating System :: OS Independent
Requires-Python: >=3.8
License-File: LICENSE
